.gitignore
CHANGES.txt
MANIFEST.in
README.txt
bootstrap.py
buildout.cfg
buildout3.cfg
setup.py
docs/INSTALL.txt
docs/LICENSE.GPL
docs/LICENSE.txt
zest/__init__.py
zest/__init__.pyc
zest.specialpaste.egg-info/PKG-INFO
zest.specialpaste.egg-info/SOURCES.txt
zest.specialpaste.egg-info/dependency_links.txt
zest.specialpaste.egg-info/entry_points.txt
zest.specialpaste.egg-info/namespace_packages.txt
zest.specialpaste.egg-info/not-zip-safe
zest.specialpaste.egg-info/requires.txt
zest.specialpaste.egg-info/top_level.txt
zest/specialpaste/__init__.py
zest/specialpaste/browser.py
zest/specialpaste/configure.zcml
zest/specialpaste/eventhandlers.py
zest/specialpaste/interfaces.py
zest/specialpaste/rebuild_i18n.sh
zest/specialpaste/testing.py
zest/specialpaste/locales/manual.pot
zest/specialpaste/locales/zest.specialpaste.pot
zest/specialpaste/locales/en/LC_MESSAGES/zest.specialpaste.mo
zest/specialpaste/locales/en/LC_MESSAGES/zest.specialpaste.po
zest/specialpaste/locales/nl/LC_MESSAGES/zest.specialpaste.mo
zest/specialpaste/locales/nl/LC_MESSAGES/zest.specialpaste.po
zest/specialpaste/profiles/default/actions.xml
zest/specialpaste/profiles/default/browserlayer.xml
zest/specialpaste/profiles/default/metadata.xml
zest/specialpaste/tests/__init__.py
zest/specialpaste/tests/test_functional.py