Metadata-Version: 1.0
Name: zest.specialpaste
Version: 1.2
Summary: Special paste action with extra options
Home-page: https://github.com/zestsoftware/zest.specialpaste
Author: Zest Software
Author-email: info@zestsoftware.nl
License: GPL
Keywords: copy paste workflow state
Platform: UNKNOWN
Classifier: Framework :: Plone
Classifier: Programming Language :: Python
